LICENSE
shello_world/__init__.py
shello_world/shello_world.py
shello_world-0.1.5.dist-info/LICENSE
shello_world-0.1.5.dist-info/METADATA
shello_world-0.1.5.dist-info/WHEEL
shello_world-0.1.5.dist-info/RECORD
